quite6/__init__.py
quite6/deferred_function.py
quite6/controller/__init__.py
quite6/controller/dialog_ui_controller.py
quite6/controller/file_dialog_controller.py
quite6/controller/widget_controller.py
quite6/controller/widget_ui_controller.py
quite6/core/__init__.py
quite6/core/event_loop.py
quite6/core/timer.py
quite6/gui/__init__.py
quite6/gui/qt_gui.py
quite6/gui/ui_extension.py
quite6/gui/interfaces/__init__.py
quite6/gui/interfaces/base_interface.py
quite6/gui/interfaces/changed_signal_interface.py
quite6/gui/interfaces/closed_signal_interface.py
quite6/gui/interfaces/excited_signal_interface.py
quite6/gui/interfaces/focus_in_signal_interface.py
quite6/gui/interfaces/focus_out_signal_interface.py
quite6/gui/interfaces/row_changed_signal_interface.py
quite6/gui/interfaces/showed_signal_interface.py
quite6/gui/interfaces/ability_interfaces/__init__.py
quite6/gui/interfaces/ability_interfaces/class_exec_interface.py
quite6/gui/interfaces/ability_interfaces/container_ability_interface.py
quite6/gui/layouts/__init__.py
quite6/gui/layouts/square_layout.py
quite6/gui/paint/__init__.py
quite6/gui/paint/painter.py
quite6/gui/paint/pen.py
quite6/gui/paint/point.py
quite6/gui/paint/scaling.py
quite6/gui/paint/size.py
quite6/gui/widgets/__init__.py
quite6/gui/widgets/action.py
quite6/gui/widgets/combo_box.py
quite6/gui/widgets/date_edit.py
quite6/gui/widgets/date_time_edit.py
quite6/gui/widgets/dialog.py
quite6/gui/widgets/dock_widget.py
quite6/gui/widgets/double_spin_box.py
quite6/gui/widgets/group_box.py
quite6/gui/widgets/input_dialog.py
quite6/gui/widgets/label.py
quite6/gui/widgets/layout.py
quite6/gui/widgets/line_edit.py
quite6/gui/widgets/list_widget.py
quite6/gui/widgets/main_window.py
quite6/gui/widgets/plot_widget.py
quite6/gui/widgets/push_button.py
quite6/gui/widgets/radio_button.py
quite6/gui/widgets/shortcut.py
quite6/gui/widgets/spin_box.py
quite6/gui/widgets/tab_widget.py
quite6/gui/widgets/table_view.py
quite6/gui/widgets/table_widget.py
quite6-1.0.9.dist-info/LICENSE
quite6-1.0.9.dist-info/METADATA
quite6-1.0.9.dist-info/WHEEL
quite6-1.0.9.dist-info/top_level.txt
quite6-1.0.9.dist-info/RECORD
